LICENSE.txt
MANIFEST.in
README
setup.cfg
setup.py
BlackRed.egg-info/PKG-INFO
BlackRed.egg-info/SOURCES.txt
BlackRed.egg-info/dependency_links.txt
BlackRed.egg-info/requires.txt
BlackRed.egg-info/top_level.txt
blackred/__init__.py
blackred/blackred.py